organizze_client/__init__.py
organizze_client/_client.py
organizze_client/_version.py
organizze_client-0.1a1.dist-info/METADATA
organizze_client-0.1a1.dist-info/WHEEL
organizze_client-0.1a1.dist-info/top_level.txt
organizze_client-0.1a1.dist-info/RECORD
